tango_admin/__init__.py
tango_admin/admin.py
tango_admin/admin_actions.py
tango_admin/forms.py
tango_admin/models.py
tango_admin/static/admin/css/base.css
tango_admin/static/admin/css/changelists.css
tango_admin/static/admin/css/forms.css
tango_admin/static/admin/css/tango_admin.css
tango_admin/static/admin/js/SelectFilter2.js
tango_admin/static/admin/js/jquery-ui-1.10.3.custom-sortable.min.js
tango_admin/static/admin/js/tango_admin_utils.js
tango_admin/templates/x-admin/base_site.html
tango_admin/templates/x-admin/blacklist.html
tango_admin/templates/x-admin/filter.html
tango_admin/templates/x-admin/inline_link_list.html
tango_admin/templates/x-admin/how-to/index.html
tango_admin/templates/x-admin/includes/app_list.html
tango_admin/templatetags/__init__.py
tango_admin/templatetags/tango_admin_tags.py
tango_admin-0.3.3.dist-info/METADATA
tango_admin-0.3.3.dist-info/RECORD
tango_admin-0.3.3.dist-info/WHEEL
tango_admin-0.3.3.dist-info/top_level.txt
