Metadata-Version: 2.1
Name: tango-admin
Version: 0.3.3
Summary: Simple admin helpers for Tango apps
Home-page: http://github.com/tBaxter/tango-admin
Author: Tim Baxter
Author-email: mail.baxter@gmail.com
License: LICENSE.txt
Platform: UNKNOWN
Requires-Dist: tango-shared-core (>=1.1)
